mohammed_way2
way2package3
