Metadata-Version: 2.1
Name: mohammed-way2
Version: 1.1
Summary: A Docker and AWS utility package
Home-page: UNKNOWN
Author: Mohammed
Author-email: mohammed.s@way2online.co.in
License: UNKNOWN
Platform: UNKNOWN
Classifier: Development Status :: 3 - Alpha
Classifier: Intended Audience :: Developers
Classifier: Topic :: Software Development :: Build Tools
Classifier: License :: OSI Approved :: MIT License
Classifier: Programming Language :: Python :: 3
Classifier: Programming Language :: Python :: 3.2
Classifier: Programming Language :: Python :: 3.3
Classifier: Programming Language :: Python :: 3.4
Requires-Python: >=3
